oppaipy/__init__.py
oppaipy/oppaipy.py
oppaipy-1.0.4.dist-info/LICENSE
oppaipy-1.0.4.dist-info/METADATA
oppaipy-1.0.4.dist-info/WHEEL
oppaipy-1.0.4.dist-info/top_level.txt
oppaipy-1.0.4.dist-info/RECORD
