Metadata-Version: 2.1
Name: oppaipy
Version: 1.0.4
Summary: A simple object-oriented python3 wrapper around the python bindings of oppai-ng
Home-page: https://github.com/Syriiin/oppaipy
Author: Syrin
Author-email: syrin@syrin.me
License: UNKNOWN
Platform: UNKNOWN
Classifier: Programming Language :: Python :: 3
Classifier: License :: OSI Approved :: MIT License
Classifier: Operating System :: OS Independent
License-File: LICENSE
Requires-Dist: oppai (~=4.1)
